ut_log/__init__.py
ut_log/__version__.py
ut_log/log.py
ut_log/py.typed
ut_log/utils.py
ut_log/cfg/__init__.py
ut_log/cfg/log.std.yml
ut_log/cfg/log.usr.yml
ut_log-2.0.0.20251020.dist-info/licenses/LICENSE.txt
ut_log-2.0.0.20251020.dist-info/METADATA
ut_log-2.0.0.20251020.dist-info/WHEEL
ut_log-2.0.0.20251020.dist-info/top_level.txt
ut_log-2.0.0.20251020.dist-info/RECORD
