Metadata-Version: 2.4
Name: ut_log
Version: 2.0.0.20251020
Summary: Utilities for Logging.
Author-email: Bernd Stroehle <bernd.stroehle@gmail.com>
Maintainer-email: Bernd Stroehle <bernd.stroehle@gmail.com>
License-Expression: GPL-3.0-only WITH Classpath-exception-2.0 OR BSD-3-Clause
Project-URL: Source Code, https://github.com/bs291048/ut_log/tree/master
Project-URL: Homepage, https://kosakya.de/
Project-URL: Documentation, https://ka-com.readthedocs.io/en/latest
Classifier: Development Status :: 5 - Production/Stable
Classifier: Intended Audience :: Developers
Classifier: Operating System :: OS Independent
Classifier: Programming Language :: Python :: 3.11
Classifier: Natural Language :: English
Classifier: Topic :: Software Development :: Libraries :: Python Modules
Requires-Python: >=3.10
License-File: LICENSE.txt
Requires-Dist: psutil>=7.0.0
Requires-Dist: pytz>=2025.1
Requires-Dist: ut_dic>=1.5.5.20251011
Requires-Dist: ut_ioc>=1.1.5.20251008
Requires-Dist: ut_pac>=1.3.1.20251017
Dynamic: license-file
